[{"id":19,"name":"Afghanistan","iso_code":"AF","region":false},{"id":1,"name":"Africa","iso_code":null,"region":true},{"id":269,"name":"Africa_Eastern","iso_code":null,"region":true},{"id":268,"name":"Africa_Northern","iso_code":null,"region":true},{"id":270,"name":"Africa_Southern","iso_code":null,"region":true},{"id":271,"name":"Africa_Western","iso_code":null,"region":true},{"id":20,"name":"Aland Islands","iso_code":"AX","region":false},{"id":21,"name":"Albania","iso_code":"AL","region":false},{"id":22,"name":"Algeria","iso_code":"DZ","region":false},{"id":23,"name":"American Samoa","iso_code":"AS","region":false},{"id":24,"name":"Andorra","iso_code":"AD","region":false},{"id":25,"name":"Angola","iso_code":"AO","region":false},{"id":26,"name":"Anguilla","iso_code":"AI","region":false},{"id":2,"name":"Annex-1","iso_code":null,"region":true},{"id":27,"name":"Antarctica","iso_code":"AQ","region":false},{"id":28,"name":"Antigua and Barbuda","iso_code":"AG","region":false},{"id":29,"name":"Argentina","iso_code":"AR","region":false},{"id":30,"name":"Armenia","iso_code":"AM","region":false},{"id":31,"name":"Aruba","iso_code":"AW","region":false},{"id":3,"name":"Asia","iso_code":null,"region":true},{"id":32,"name":"Australia","iso_code":"AU","region":false},{"id":4,"name":"Australia/New Zealand","iso_code":null,"region":true},{"id":33,"name":"Austria","iso_code":"AT","region":false},{"id":34,"name":"Azerbaijan","iso_code":"AZ","region":false},{"id":35,"name":"Bahamas","iso_code":"BS","region":false},{"id":36,"name":"Bahrain","iso_code":"BH","region":false},{"id":37,"name":"Bangladesh","iso_code":"BD","region":false},{"id":38,"name":"Barbados","iso_code":"BB","region":false},{"id":39,"name":"Belarus","iso_code":"BY","region":false},{"id":40,"name":"Belgium","iso_code":"BE","region":false},{"id":41,"name":"Belize","iso_code":"BZ","region":false},{"id":42,"name":"Benin","iso_code":"BJ","region":false},{"id":43,"name":"Bermuda","iso_code":"BM","region":false},{"id":44,"name":"Bhutan","iso_code":"BT","region":false},{"id":45,"name":"Bolivia","iso_code":"BO","region":false},{"id":46,"name":"Bosnia and Herzegovina","iso_code":"BA","region":false},{"id":47,"name":"Botswana","iso_code":"BW","region":false},{"id":48,"name":"Bouvet Island","iso_code":"BV","region":false},{"id":49,"name":"Brazil","iso_code":"BR","region":false},{"id":51,"name":"British Indian Ocean Territory","iso_code":"IO","region":false},{"id":50,"name":"British Virgin Islands","iso_code":"VG","region":false},{"id":52,"name":"Brunei Darussalam","iso_code":"BN","region":false},{"id":53,"name":"Bulgaria","iso_code":"BG","region":false},{"id":54,"name":"Burkina Faso","iso_code":"BF","region":false},{"id":55,"name":"Burundi","iso_code":"BI","region":false},{"id":56,"name":"Cambodia","iso_code":"KH","region":false},{"id":57,"name":"Cameroon","iso_code":"CM","region":false},{"id":58,"name":"Canada","iso_code":"CA","region":false},{"id":59,"name":"Cape Verde","iso_code":"CV","region":false},{"id":60,"name":"Cayman Islands","iso_code":"KY","region":false},{"id":61,"name":"Central African Republic","iso_code":"CF","region":false},{"id":272,"name":"Central America and Caribbean","iso_code":null,"region":true},{"id":5,"name":"Central Asia","iso_code":null,"region":true},{"id":62,"name":"Chad","iso_code":"TD","region":false},{"id":63,"name":"Chile","iso_code":"CL","region":false},{"id":64,"name":"China","iso_code":"CN","region":false},{"id":67,"name":"Christmas Island","iso_code":"CX","region":false},{"id":68,"name":"Cocos Islands","iso_code":"CC","region":false},{"id":69,"name":"Colombia","iso_code":"CO","region":false},{"id":70,"name":"Comoros","iso_code":"KM","region":false},{"id":72,"name":"Congo Kinshasa","iso_code":"CD","region":false},{"id":71,"name":"Congo Brazzaville","iso_code":"CG","region":false},{"id":73,"name":"Cook Islands","iso_code":"CK","region":false},{"id":74,"name":"Costa Rica","iso_code":"CR","region":false},{"id":75,"name":"Côte d'Ivoire","iso_code":"CI","region":false},{"id":76,"name":"Croatia","iso_code":"HR","region":false},{"id":77,"name":"Cuba","iso_code":"CU","region":false},{"id":78,"name":"Cyprus","iso_code":"CY","region":false},{"id":79,"name":"Czech Republic","iso_code":"CZ","region":false},{"id":80,"name":"Denmark","iso_code":"DK","region":false},{"id":81,"name":"Djibouti","iso_code":"DJ","region":false},{"id":82,"name":"Dominica","iso_code":"DM","region":false},{"id":83,"name":"Dominican Republic","iso_code":"DO","region":false},{"id":6,"name":"East Asia and Pacific","iso_code":null,"region":true},{"id":84,"name":"Ecuador","iso_code":"EC","region":false},{"id":85,"name":"Egypt","iso_code":"EG","region":false},{"id":86,"name":"El Salvador","iso_code":"SV","region":false},{"id":87,"name":"Equatorial Guinea","iso_code":"GQ","region":false},{"id":88,"name":"Eritrea","iso_code":"ER","region":false},{"id":89,"name":"Estonia","iso_code":"EE","region":false},{"id":90,"name":"Ethiopia","iso_code":"ET","region":false},{"id":273,"name":"EU-12","iso_code":null,"region":true},{"id":274,"name":"EU-15","iso_code":null,"region":true},{"id":7,"name":"Europe","iso_code":null,"region":true},{"id":277,"name":"European Free Trade Association","iso_code":null,"region":true},{"id":265,"name":"European Union","iso_code":null,"region":true},{"id":275,"name":"Europe_Eastern","iso_code":null,"region":true},{"id":276,"name":"Europe_Non_EU","iso_code":null,"region":true},{"id":91,"name":"Falkland Islands","iso_code":"FK","region":false},{"id":92,"name":"Faroe Islands","iso_code":"FO","region":false},{"id":93,"name":"Fiji","iso_code":"FJ","region":false},{"id":94,"name":"Finland","iso_code":"FI","region":false},{"id":95,"name":"France","iso_code":"FR","region":false},{"id":96,"name":"French Guiana","iso_code":"GF","region":false},{"id":97,"name":"French Polynesia","iso_code":"PF","region":false},{"id":98,"name":"French Southern Territories","iso_code":"TF","region":false},{"id":8,"name":"G20","iso_code":null,"region":true},{"id":99,"name":"Gabon","iso_code":"GA","region":false},{"id":100,"name":"Gambia","iso_code":"GM","region":false},{"id":101,"name":"Georgia","iso_code":"GE","region":false},{"id":102,"name":"Germany","iso_code":"DE","region":false},{"id":103,"name":"Ghana","iso_code":"GH","region":false},{"id":104,"name":"Gibraltar","iso_code":"GI","region":false},{"id":105,"name":"Greece","iso_code":"GR","region":false},{"id":106,"name":"Greenland","iso_code":"GL","region":false},{"id":107,"name":"Grenada","iso_code":"GD","region":false},{"id":108,"name":"Guadeloupe","iso_code":"GP","region":false},{"id":109,"name":"Guam","iso_code":"GU","region":false},{"id":110,"name":"Guatemala","iso_code":"GT","region":false},{"id":111,"name":"Guernsey","iso_code":"GG","region":false},{"id":112,"name":"Guinea","iso_code":"GN","region":false},{"id":113,"name":"Guinea-Bissau","iso_code":"GW","region":false},{"id":114,"name":"Guyana","iso_code":"GY","region":false},{"id":115,"name":"Haiti","iso_code":"HT","region":false},{"id":116,"name":"Heard and Mcdonald Islands","iso_code":"HM","region":false},{"id":117,"name":"Honduras","iso_code":"HN","region":false},{"id":65,"name":"Hong Kong","iso_code":"HK","region":false},{"id":118,"name":"Hungary","iso_code":"HU","region":false},{"id":119,"name":"Iceland","iso_code":"IS","region":false},{"id":120,"name":"India","iso_code":"IN","region":false},{"id":121,"name":"Indonesia","iso_code":"ID","region":false},{"id":122,"name":"Iran","iso_code":"IR","region":false},{"id":123,"name":"Iraq","iso_code":"IQ","region":false},{"id":124,"name":"Ireland","iso_code":"IE","region":false},{"id":125,"name":"Isle of Man","iso_code":"IM","region":false},{"id":126,"name":"Israel","iso_code":"IL","region":false},{"id":127,"name":"Italy","iso_code":"IT","region":false},{"id":128,"name":"Jamaica","iso_code":"JM","region":false},{"id":129,"name":"Japan","iso_code":"JP","region":false},{"id":130,"name":"Jersey","iso_code":"JE","region":false},{"id":131,"name":"Jordan","iso_code":"JO","region":false},{"id":132,"name":"Kazakhstan","iso_code":"KZ","region":false},{"id":133,"name":"Kenya","iso_code":"KE","region":false},{"id":134,"name":"Kiribati","iso_code":"KI","region":false},{"id":137,"name":"Kuwait","iso_code":"KW","region":false},{"id":138,"name":"Kyrgyzstan","iso_code":"KG","region":false},{"id":139,"name":"Lao","iso_code":"LA","region":false},{"id":9,"name":"Latin America and Caribbean","iso_code":null,"region":true},{"id":140,"name":"Latvia","iso_code":"LV","region":false},{"id":141,"name":"Lebanon","iso_code":"LB","region":false},{"id":142,"name":"Lesotho","iso_code":"LS","region":false},{"id":143,"name":"Liberia","iso_code":"LR","region":false},{"id":144,"name":"Libya","iso_code":"LY","region":false},{"id":145,"name":"Liechtenstein","iso_code":"LI","region":false},{"id":146,"name":"Lithuania","iso_code":"LT","region":false},{"id":147,"name":"Luxembourg","iso_code":"LU","region":false},{"id":66,"name":"Macao","iso_code":"MO","region":false},{"id":148,"name":"Macedonia","iso_code":"MK","region":false},{"id":149,"name":"Madagascar","iso_code":"MG","region":false},{"id":150,"name":"Malawi","iso_code":"MW","region":false},{"id":151,"name":"Malaysia","iso_code":"MY","region":false},{"id":152,"name":"Maldives","iso_code":"MV","region":false},{"id":153,"name":"Mali","iso_code":"ML","region":false},{"id":154,"name":"Malta","iso_code":"MT","region":false},{"id":155,"name":"Marshall Islands","iso_code":"MH","region":false},{"id":156,"name":"Martinique","iso_code":"MQ","region":false},{"id":157,"name":"Mauritania","iso_code":"MR","region":false},{"id":158,"name":"Mauritius","iso_code":"MU","region":false},{"id":159,"name":"Mayotte","iso_code":"YT","region":false},{"id":160,"name":"Mexico","iso_code":"MX","region":false},{"id":266,"name":"Mexico/Chile","iso_code":null,"region":true},{"id":161,"name":"Micronesia","iso_code":"FM","region":false},{"id":10,"name":"Middle East","iso_code":null,"region":true},{"id":11,"name":"Middle East and North Africa","iso_code":null,"region":true},{"id":162,"name":"Moldova","iso_code":"MD","region":false},{"id":163,"name":"Monaco","iso_code":"MC","region":false},{"id":164,"name":"Mongolia","iso_code":"MN","region":false},{"id":165,"name":"Montenegro","iso_code":"ME","region":false},{"id":166,"name":"Montserrat","iso_code":"MS","region":false},{"id":167,"name":"Morocco","iso_code":"MA","region":false},{"id":168,"name":"Mozambique","iso_code":"MZ","region":false},{"id":169,"name":"Myanmar","iso_code":"MM","region":false},{"id":170,"name":"Namibia","iso_code":"NA","region":false},{"id":171,"name":"Nauru","iso_code":"NR","region":false},{"id":172,"name":"Nepal","iso_code":"NP","region":false},{"id":173,"name":"Netherlands","iso_code":"NL","region":false},{"id":174,"name":"Netherlands Antilles","iso_code":"AN","region":false},{"id":175,"name":"New Caledonia","iso_code":"NC","region":false},{"id":176,"name":"New Zealand","iso_code":"NZ","region":false},{"id":177,"name":"Nicaragua","iso_code":"NI","region":false},{"id":178,"name":"Niger","iso_code":"NE","region":false},{"id":179,"name":"Nigeria","iso_code":"NG","region":false},{"id":180,"name":"Niue","iso_code":"NU","region":false},{"id":181,"name":"Norfolk Island","iso_code":"NF","region":false},{"id":12,"name":"North America","iso_code":null,"region":true},{"id":182,"name":"Northern Mariana Islands","iso_code":"MP","region":false},{"id":135,"name":"North Korea","iso_code":"KP","region":false},{"id":183,"name":"Norway","iso_code":"NO","region":false},{"id":13,"name":"OECD","iso_code":null,"region":true},{"id":184,"name":"Oman","iso_code":"OM","region":false},{"id":185,"name":"Pakistan","iso_code":"PK","region":false},{"id":186,"name":"Palau","iso_code":"PW","region":false},{"id":187,"name":"Palestinian Territory","iso_code":"PS","region":false},{"id":188,"name":"Panama","iso_code":"PA","region":false},{"id":189,"name":"Papua New Guinea","iso_code":"PG","region":false},{"id":190,"name":"Paraguay","iso_code":"PY","region":false},{"id":191,"name":"Peru","iso_code":"PE","region":false},{"id":192,"name":"Philippines","iso_code":"PH","region":false},{"id":193,"name":"Pitcairn","iso_code":"PN","region":false},{"id":194,"name":"Poland","iso_code":"PL","region":false},{"id":195,"name":"Portugal","iso_code":"PT","region":false},{"id":196,"name":"Puerto Rico","iso_code":"PR","region":false},{"id":197,"name":"Qatar","iso_code":"QA","region":false},{"id":198,"name":"Réunion","iso_code":"RE","region":false},{"id":199,"name":"Romania","iso_code":"RO","region":false},{"id":200,"name":"Russia","iso_code":"RU","region":false},{"id":201,"name":"Rwanda","iso_code":"RW","region":false},{"id":202,"name":"Saint-Barthélemy","iso_code":"BL","region":false},{"id":203,"name":"Saint Helena","iso_code":"SH","region":false},{"id":204,"name":"Saint Kitts and Nevis","iso_code":"KN","region":false},{"id":205,"name":"Saint Lucia","iso_code":"LC","region":false},{"id":206,"name":"Saint-Martin","iso_code":"MF","region":false},{"id":207,"name":"Saint Pierre and Miquelon","iso_code":"PM","region":false},{"id":208,"name":"Saint Vincent and Grenadines","iso_code":"VC","region":false},{"id":209,"name":"Samoa","iso_code":"WS","region":false},{"id":210,"name":"San Marino","iso_code":"SM","region":false},{"id":211,"name":"Sao Tome and Principe","iso_code":"ST","region":false},{"id":212,"name":"Saudi Arabia","iso_code":"SA","region":false},{"id":213,"name":"Senegal","iso_code":"SN","region":false},{"id":214,"name":"Serbia","iso_code":"RS","region":false},{"id":215,"name":"Seychelles","iso_code":"SC","region":false},{"id":216,"name":"Sierra Leone","iso_code":"SL","region":false},{"id":217,"name":"Singapore","iso_code":"SG","region":false},{"id":218,"name":"Slovakia","iso_code":"SK","region":false},{"id":219,"name":"Slovenia","iso_code":"SI","region":false},{"id":220,"name":"Solomon Islands","iso_code":"SB","region":false},{"id":221,"name":"Somalia","iso_code":"SO","region":false},{"id":222,"name":"South Africa","iso_code":"ZA","region":false},{"id":15,"name":"South America","iso_code":null,"region":true},{"id":278,"name":"South America_Northern","iso_code":null,"region":true},{"id":279,"name":"South America_Southern","iso_code":null,"region":true},{"id":16,"name":"South Asia","iso_code":null,"region":true},{"id":17,"name":"Southeast Asia","iso_code":null,"region":true},{"id":223,"name":"South Georgia and the South Sandwich Islands","iso_code":"GS","region":false},{"id":136,"name":"South Korea","iso_code":"KR","region":false},{"id":224,"name":"South Sudan","iso_code":"SS","region":false},{"id":225,"name":"Spain","iso_code":"ES","region":false},{"id":226,"name":"Sri Lanka","iso_code":"LK","region":false},{"id":227,"name":"Sudan","iso_code":"SD","region":false},{"id":228,"name":"Suriname","iso_code":"SR","region":false},{"id":229,"name":"Svalbard and Jan Mayen Islands","iso_code":"SJ","region":false},{"id":230,"name":"Swaziland","iso_code":"SZ","region":false},{"id":231,"name":"Sweden","iso_code":"SE","region":false},{"id":232,"name":"Switzerland","iso_code":"CH","region":false},{"id":233,"name":"Syria","iso_code":"SY","region":false},{"id":234,"name":"Taiwan","iso_code":"TW","region":false},{"id":235,"name":"Tajikistan","iso_code":"TJ","region":false},{"id":236,"name":"Tanzania","iso_code":"TZ","region":false},{"id":237,"name":"Thailand","iso_code":"TH","region":false},{"id":238,"name":"Timor-Leste","iso_code":"TL","region":false},{"id":239,"name":"Togo","iso_code":"TG","region":false},{"id":240,"name":"Tokelau","iso_code":"TK","region":false},{"id":241,"name":"Tonga","iso_code":"TO","region":false},{"id":242,"name":"Trinidad and Tobago","iso_code":"TT","region":false},{"id":243,"name":"Tunisia","iso_code":"TN","region":false},{"id":244,"name":"Turkey","iso_code":"TR","region":false},{"id":245,"name":"Turkmenistan","iso_code":"TM","region":false},{"id":246,"name":"Turks and Caicos Islands","iso_code":"TC","region":false},{"id":247,"name":"Tuvalu","iso_code":"TV","region":false},{"id":248,"name":"Uganda","iso_code":"UG","region":false},{"id":249,"name":"Ukraine","iso_code":"UA","region":false},{"id":250,"name":"United Arab Emirates","iso_code":"AE","region":false},{"id":251,"name":"United Kingdom","iso_code":"GB","region":false},{"id":18,"name":"United States","iso_code":"US","region":false},{"id":254,"name":"Uruguay","iso_code":"UY","region":false},{"id":253,"name":"US Minor Outlying Islands","iso_code":"UM","region":false},{"id":259,"name":"US Virgin Islands","iso_code":"VI","region":false},{"id":255,"name":"Uzbekistan","iso_code":"UZ","region":false},{"id":256,"name":"Vanuatu","iso_code":"VU","region":false},{"id":257,"name":"Venezuela","iso_code":"VE","region":false},{"id":258,"name":"Viet Nam","iso_code":"VN","region":false},{"id":260,"name":"Wallis and Futuna Islands","iso_code":"WF","region":false},{"id":261,"name":"Western Sahara","iso_code":"EH","region":false},{"id":267,"name":"World","iso_code":null,"region":true},{"id":262,"name":"Yemen","iso_code":"YE","region":false},{"id":263,"name":"Zambia","iso_code":"ZM","region":false},{"id":264,"name":"Zimbabwe","iso_code":"ZW","region":false}]
